Workbook

Sheet Supply Chain
A1: Order_ID | B1: Customer_ID | C1: Order_Date | D1: Ship_Date | E1: Ship_Mode | F1: Region | G1: Country | H1: City | I1: Product_ID | J1: Category | K1: Sub_Category | L1: Product_Name | M1: Unit_Price | N1: Quantity | O1: Supplier_ID | P1: Supplier_Name | Q1: Warehouse_ID | R1: Transport_Mode | S1: Carrier | T1: Route | U1: Stock_On_Hand | V1: Reorder_Level | W1: Lead_Time_Days | X1: Procurement_Cost | Y1: Transportation_Cost | Z1: Total_Cost | AA1: Delivery_Status | AB1: Delay_Days | AC1: Fill_Rate | AD1: Forecast_Demand | AE1: Actual_Demand
A2: O1000000 | B2: C6915 | C2: 44823 | D2: 44160 | E2: Same-day | F2: Asia | G2: USA | H2: New York | I2: P11470 | J2: Electronics | K2: Snacks | L2: Product_2649 | M2: 373.69 | N2: 55 | O2: S933 | P2: Alpha Corp | Q2: W10 | R2: Air | S2: FedEx | T2: Beijing-New York | U2: 4259 | V2: 214 | W2: 9 | X2: 1474.56 | Y2: 406.15 | Z2: 1880.71 | AA2: Delayed | AB2: 8 | AC2: 93.39 | AD2: 341 | AE2: 291
A3: O1000001 | B3: C5679 | C3: 44555 | D3: 44119 | E3: Express | F3: North America | G3: India | H3: Berlin | I3: P31237 | J3: Food | K3: Medicines | L3: Product_5052 | M3: 264.69 | N3: 3 | O3: S987 | P3: Delta Traders | Q3: W49 | R3: Road | S3: FedEx | T3: Toronto-Cape Town | U3: 1173 | V3: 386 | W3: 24 | X3: 1874.56 | Y3: 421.77 | Z3: 2296.33 | AA3: On-time | AB3: 0 | AC3: 95.29 | AD3: 482 | AE3: 477 | AH3: =COUNTIF(AA2:AA1001,"On-time")/COUNTA(AA2:AA1001) -> 0.9
A4: O1000002 | B4: C3498 | C4: 44045 | D4: 45123 | E4: Standard | F4: North America | G4: Canada | H4: Mumbai | I4: P97172 | J4: Electronics | K4: Laptop | L4: Product_3438 | M4: 497.44 | N4: 80 | O4: S822 | P4: Alpha Corp | Q4: W38 | R4: Air | S4: DHL | T4: São Paulo-Cape Town | U4: 588 | V4: 398 | W4: 27 | X4: 439.67 | Y4: 289.19 | Z4: 728.86 | AA4: On-time | AB4: 0 | AC4: 76.63 | AD4: 461 | AE4: 476
A5: O1000003 | B5: C8748 | C5: 44845 | D5: 44888 | E5: Express | F5: South America | G5: China | H5: Toronto | I5: P95052 | J5: Apparel | K5: Chair | L5: Product_1125 | M5: 266.87 | N5: 44 | O5: S114 | P5: Gamma Inc | Q5: W45 | R5: Rail | S5: Maersk | T5: Cape Town-Toronto | U5: 4700 | V5: 381 | W5: 29 | X5: 1378.1 | Y5: 321.73 | Z5: 1699.83 | AA5: On-time | AB5: 0 | AC5: 85.24 | AD5: 150 | AE5: 198
A6: O1000004 | B6: C7620 | C6: 44403 | D6: 45340 | E6: Standard | F6: Africa | G6: UK | H6: Berlin | I6: P76170 | J6: Pharma | K6: Shirt | L6: Product_7942 | M6: 360.94 | N6: 18 | O6: S554 | P6: Delta Traders | Q6: W16 | R6: Rail | S6: BlueDart | T6: Berlin-São Paulo | U6: 1795 | V6: 415 | W6: 27 | X6: 861.29 | Y6: 351.29 | Z6: 1212.58 | AA6: On-time | AB6: 0 | AC6: 86.44 | AD6: 89 | AE6: 93
A7: O1000005 | B7: C2078 | C7: 45254 | D7: 44602 | E7: Express | F7: North America | G7: Germany | H7: New York | I7: P74006 | J7: Furniture | K7: Shirt | L7: Product_5026 | M7: 172.93 | N7: 35 | O7: S135 | P7: Epsilon LLC | Q7: W15 | R7: Road | S7: DHL | T7: Toronto-Toronto | U7: 1159 | V7: 228 | W7: 13 | X7: 690.34 | Y7: 410.07 | Z7: 1100.41 | AA7: On-time | AB7: 0 | AC7: 88.12 | AD7: 348 | AE7: 325
A8: O1000006 | B8: C6228 | C8: 45515 | D8: 45601 | E8: Standard | F8: Africa | G8: South Africa | H8: São Paulo | I8: P48808 | J8: Electronics | K8: Snacks | L8: Product_3099 | M8: 103.93 | N8: 38 | O8: S974 | P8: Gamma Inc | Q8: W34 | R8: Rail | S8: Maersk | T8: Cape Town-São Paulo | U8: 3330 | V8: 425 | W8: 28 | X8: 1828.88 | Y8: 314.18 | Z8: 2143.06 | AA8: On-time | AB8: 0 | AC8: 93.23 | AD8: 488 | AE8: 511
A9: O1000007 | B9: C7718 | C9: 44286 | D9: 44938 | E9: Standard | F9: Asia | G9: China | H9: New York | I9: P44869 | J9: Apparel | K9: Shirt | L9: Product_9956 | M9: 130.35 | N9: 32 | O9: S154 | P9: Alpha Corp | Q9: W6 | R9: Road | S9: UPS | T9: Berlin-New York | U9: 4252 | V9: 229 | W9: 22 | X9: 468.41 | Y9: 453.18 | Z9: 921.59 | AA9: On-time | AB9: 0 | AC9: 86.46 | AD9: 425 | AE9: 378
A10: O1000008 | B10: C3973 | C10: 44920 | D10: 45145 | E10: Express | F10: Asia | G10: China | H10: Berlin | I10: P71314 | J10: Electronics | K10: Medicines | L10: Product_8108 | M10: 45.53 | N10: 27 | O10: S357 | P10: Alpha Corp | Q10: W25 | R10: Rail | S10: UPS | T10: New York-Beijing | U10: 1395 | V10: 419 | W10: 27 | X10: 1249.1 | Y10: 147.27 | Z10: 1396.37 | AA10: Delayed | AB10: 5 | AC10: 98.59 | AD10: 379 | AE10: 402
A11: O1000009 | B11: C1323 | C11: 43854 | D11: 44262 | E11: Express | F11: Asia | G11: Germany | H11: New York | I11: P89439 | J11: Food | K11: Snacks | L11: Product_6620 | M11: 65.62 | N11: 65 | O11: S160 | P11: Beta Ltd | Q11: W5 | R11: Air | S11: UPS | T11: London-Berlin | U11: 1590 | V11: 246 | W11: 29 | X11: 1632.88 | Y11: 415.97 | Z11: 2048.85 | AA11: Delayed | AB11: 11 | AC11: 84.77 | AD11: 300 | AE11: 306
A12: O1000010 | B12: C3178 | C12: 43854 | D12: 44059 | E12: Same-day | F12: Europe | G12: USA | H12: Beijing | I12: P30947 | J12: Pharma | K12: Shirt | L12: Product_2942 | M12: 309.55 | N12: 93 | O12: S132 | P12: Alpha Corp | Q12: W4 | R12: Sea | S12: DHL | T12: Mumbai-Cape Town | U12: 2116 | V12: 291 | W12: 4 | X12: 384.63 | Y12: 337.66 | Z12: 722.29 | AA12: On-time | AB12: 0 | AC12: 94.8 | AD12: 425 | AE12: 386
A13: O1000011 | B13: C3505 | C13: 45631 | D13: 44030 | E13: Express | F13: Europe | G13: China | H13: Berlin | I13: P88708 | J13: Electronics | K13: Shirt | L13: Product_7793 | M13: 186.56 | N13: 93 | O13: S546 | P13: Alpha Corp | Q13: W47 | R13: Road | S13: UPS | T13: Cape Town-Mumbai | U13: 4911 | V13: 358 | W13: 18 | X13: 706.31 | Y13: 293.54 | Z13: 999.85 | AA13: On-time | AB13: 0 | AC13: 70.02 | AD13: 257 | AE13: 257
A14: O1000012 | B14: C4735 | C14: 45194 | D14: 44024 | E14: Standard | F14: South America | G14: South Africa | H14: Cape Town | I14: P83879 | J14: Furniture | K14: Snacks | L14: Product_5247 | M14: 88.2 | N14: 91 | O14: S468 | P14: Epsilon LLC | Q14: W29 | R14: Rail | S14: DHL | T14: Beijing-London | U14: 2805 | V14: 490 | W14: 2 | X14: 1263.24 | Y14: 80.16 | Z14: 1343.4 | AA14: On-time | AB14: 0 | AC14: 76.64 | AD14: 428 | AE14: 434
A15: O1000013 | B15: C1316 | C15: 45272 | D15: 45403 | E15: Standard | F15: South America | G15: South Africa | H15: São Paulo | I15: P57583 | J15: Apparel | K15: Shirt | L15: Product_5819 | M15: 165.4 | N15: 55 | O15: S674 | P15: Delta Traders | Q15: W1 | R15: Air | S15: DHL | T15: Berlin-Cape Town | U15: 4728 | V15: 220 | W15: 26 | X15: 1831.52 | Y15: 70.27 | Z15: 1901.79 | AA15: Delayed | AB15: 10 | AC15: 91.19 | AD15: 252 | AE15: 222
... A1001: O1000999 | B1001: C3295 | C1001: 45252 | D1001: 44488 | E1001: Standard | F1001: North America | G1001: Canada | H1001: New York | I1001: P44832 | J1001: Food | K1001: Chair | L1001: Product_4306 | M1001: 462.35 | N1001: 4 | O1001: S485 | P1001: Alpha Corp | Q1001: W13 | R1001: Sea | S1001: DHL | T1001: London-Toronto | U1001: 4955 | V1001: 246 | W1001: 23 | X1001: 1167.01 | Y1001: 117.86 | Z1001: 1284.87 | AA1001: On-time | AB1001: 0 | AC1001: 71.28 | AD1001: 122 | AE1001: 91

Sheet Order & Sales KPIs
C5: Total Orders | D5: =COUNTA('Supply Chain'!A2:A1001) -> 1000
D7: Sum of unit | E7: Sum of quan
C8: Total Sales Revenue | D8: =SUM('Supply Chain'!M2:M1001) -> 254219.11 | E8: =SUM('Supply Chain'!N2:N1001) -> 49343 | F8: =SUM(D8*E8) -> 1.2543934e+10
D9: Sum of unit | E9: Sum of quan | F9: Total Orders
D10: =SUM('Supply Chain'!M2:M1001) -> 254219.11 | E10: =SUM('Supply Chain'!N2:N1001) -> 49343 | F10: =COUNTA('Supply Chain'!A2:A1001) -> 1000
C11: Average Order Value | D11: =SUM(D10*E10)/F10 -> 12543934

Sheet Inventory & Stock KPIs
C6: Stock on Hand | D6: =SUM('Supply Chain'!U2:U1001) -> 2484173
C10: Average Lead Time | D10: =AVERAGE('Supply Chain'!W2:W1001) -> 14.637
C12: Inventory Turnover Ratio
D14: =SUM('Supply Chain'!Z2:Z1001) -> 1278382.9 | E14: =SUM('Supply Chain'!U2:U1001) -> 2484173
D15: =D14/E14 -> 0.51461105

Sheet Procurement & Cost KPIs
C5: Procurement Cost | D5: =SUM('Supply Chain'!X2:X1001) -> 1015919.5
C7: Transportation Cost | D7: =SUM('Supply Chain'!Y2:Y1001) -> 262463.43
C9: Total Supply Chain Cost | D9: =SUM('Supply Chain'!Z2:Z1001) -> 1278382.9
C11: Cost per Unit | D11: total cost | E11: Sum of qty
D12: =SUM('Supply Chain'!Z2:Z1001) -> 1278382.9 | E12: =SUM('Supply Chain'!N2:N1001) -> 49343
D13: =D12/E12 -> 25.90809

Sheet Logistics & Delivery KPIs
C7: Average Delay | D7: =AVERAGE('Supply Chain'!AB2:AB1001) -> 0.789
C9: Orders by Ship Mode
F11: Row Labels | G11: Count of Order_ID
F12: Express | G12: 285
F13: Same-day | G13: 88
F14: Standard | G14: 627
F15: Grand Total | G15: 1000
C17: Transport Mode Utilization
F18: Row Labels | G18: Count of Order_ID
F19: Air | G19: 254
F20: Rail | G20: 251
F21: Road | G21: 253
F22: Sea | G22: 242
F23: Grand Total | G23: 1000
C25: On-Time Delivery %
F27: =COUNTIF('Supply Chain'!AA2:AA1001,"On-time")/COUNTA('Supply Chain'!AA2:AA1001) -> 0.9

Sheet Demand & Fulfillment KPIs
B6: Forecast Accuracy | C6: =ABS('Supply Chain'!AD2:AD1001-'Supply Chain'!AE2:AE1001)/'Supply Chain'!AD2:AD1001 -> 0.04494382
B7: Fill Rate | C7: =AVERAGE('Supply Chain'!AC2:AC1001) -> 84.71154

Sheet Dashboard
C4: Row Labels | D4: Count of Order_ID
C5: Express | D5: 285
C6: Same-day | D6: 88
C7: Standard | D7: 627
C8: Grand Total | D8: 1000
C9: Row Labels | D9: Count of Order_ID
C10: Air | D10: 254
C11: Rail | D11: 251
C12: Road | D12: 253
C13: Sea | D13: 242
C14: Grand Total | D14: 1000
